grid_draw/__init__.py
grid_draw/envs/__init__.py
grid_draw/envs/grid_draw_bw.py
grid_draw/envs/grid_draw_rgb.py
grid_draw-0.0.5.dist-info/METADATA
grid_draw-0.0.5.dist-info/RECORD
grid_draw-0.0.5.dist-info/WHEEL
grid_draw-0.0.5.dist-info/top_level.txt
