Metadata-Version: 2.1
Name: grid-draw
Version: 0.0.5
Summary: An OpenAI Gym Environment to draw on a grid.
Home-page: https://github.com/te95/grid_draw
Author: Thomas Edlich
Author-email: thomas.edlich@icloud.com
License: MIT
Platform: UNKNOWN
Requires-Dist: gym
Requires-Dist: numpy
